azdevops/__init__.py
azdevops/auth.py
azdevops/azdev.py
azdevops/azdev_show.py
azdevops/azdevclient.py
azdevops/issue.py
azdevops/misc.py
azdevops/pipelines.py
azdevops/project.py
azdevops/search.py
azdevops/sendgrid.py
azdevops/sprints.py
goatazdevops-2024.7.16.1622.dist-info/METADATA
goatazdevops-2024.7.16.1622.dist-info/WHEEL
goatazdevops-2024.7.16.1622.dist-info/entry_points.txt
goatazdevops-2024.7.16.1622.dist-info/top_level.txt
goatazdevops-2024.7.16.1622.dist-info/RECORD
